{
"highlevel": {
    "danceability": {
        "all": {
            "danceable": 0.98482465744,
            "not_danceable": 0.0151753472164
        },
        "probability": 0.98482465744,
        "value": "danceable"
    },
    "gender": {
        "all": {
            "female": 0.640674352646,
            "male": 0.359325647354
        },
        "probability": 0.640674352646,
        "value": "female"
    },
    "genre_dortmund": {
        "all": {
            "alternative": 0.047824010253,
            "blues": 0.17856733501,
            "electronic": 0.0581084005535,
            "folkcountry": 0.10277300328,
            "funksoulrnb": 0.0172821059823,
            "jazz": 0.143841356039,
            "pop": 0.082893230021,
            "raphiphop": 0.241400286555,
            "rock": 0.12731026113
        },
        "probability": 0.241400286555,
        "value": "raphiphop"
    },
    "genre_electronic": {
        "all": {
            "ambient": 0.641426801682,
            "dnb": 0.0958842113614,
            "house": 0.187094822526,
            "techno": 0.0428697504103,
            "trance": 0.0327243991196
        },
        "probability": 0.641426801682,
        "value": "ambient"
    },
    "genre_rosamerica": {
        "all": {
            "cla": 0.0183213334531,
            "dan": 0.0225426834077,
            "hip": 0.134339407086,
            "jaz": 0.130215540528,
            "pop": 0.0740296319127,
            "rhy": 0.552224874496,
            "roc": 0.0262604113668,
            "spe": 0.0420661121607
        },
        "probability": 0.552224874496,
        "value": "rhy"
    },
    "genre_tzanetakis": {
        "all": {
            "blu": 0.0622663982213,
            "cla": 0.0345780998468,
            "cou": 0.103735685349,
            "dis": 0.0518908686936,
            "hip": 0.155698984861,
            "jaz": 0.311586618423,
            "met": 0.0519040971994,
            "pop": 0.0622744634748,
            "reg": 0.0622723288834,
            "roc": 0.103792458773
        },
        "probability": 0.311586618423,
        "value": "jaz"
    },
    "ismir04_rhythm": {
        "all": {
            "ChaChaCha": 0.00762259121984,
            "Jive": 0.00707027455792,
            "Quickstep": 0.0566461496055,
            "Rumba-American": 0.0115640191361,
            "Rumba-International": 0.766829252243,
            "Rumba-Misc": 0.0250437688082,
            "Samba": 0.0857906639576,
            "Tango": 0.00317844981328,
            "VienneseWaltz": 0.0192785784602,
            "Waltz": 0.0169762670994
        },
        "probability": 0.766829252243,
        "value": "Rumba-International"
    },
    "mood_acoustic": {
        "all": {
            "acoustic": 0.467055588961,
            "not_acoustic": 0.532944381237
        },
        "probability": 0.532944381237,
        "value": "not_acoustic"
    },
    "mood_aggressive": {
        "all": {
            "aggressive": 0.0949295908213,
            "not_aggressive": 0.90507042408
        },
        "probability": 0.90507042408,
        "value": "not_aggressive"
    },
    "mood_electronic": {
        "all": {
            "electronic": 0.631400465965,
            "not_electronic": 0.368599534035
        },
        "probability": 0.631400465965,
        "value": "electronic"
    },
    "mood_happy": {
        "all": {
            "happy": 0.0610213577747,
            "not_happy": 0.938978612423
        },
        "probability": 0.938978612423,
        "value": "not_happy"
    },
    "mood_party": {
        "all": {
            "not_party": 0.625002026558,
            "party": 0.374997973442
        },
        "probability": 0.625002026558,
        "value": "not_party"
    },
    "mood_relaxed": {
        "all": {
            "not_relaxed": 0.0711841881275,
            "relaxed": 0.928815841675
        },
        "probability": 0.928815841675,
        "value": "relaxed"
    },
    "mood_sad": {
        "all": {
            "not_sad": 0.383450090885,
            "sad": 0.616549909115
        },
        "probability": 0.616549909115,
        "value": "sad"
    },
    "moods_mirex": {
        "all": {
            "Cluster1": 0.417369812727,
            "Cluster2": 0.290512800217,
            "Cluster3": 0.223458021879,
            "Cluster4": 0.0365387871861,
            "Cluster5": 0.0321205593646
        },
        "probability": 0.417369812727,
        "value": "Cluster1"
    },
    "timbre": {
        "all": {
            "bright": 0.252188324928,
            "dark": 0.747811675072
        },
        "probability": 0.747811675072,
        "value": "dark"
    },
    "tonal_atonal": {
        "all": {
            "atonal": 0.527860701084,
            "tonal": 0.472139269114
        },
        "probability": 0.527860701084,
        "value": "atonal"
    },
    "voice_instrumental": {
        "all": {
            "instrumental": 0.472820430994,
            "voice": 0.527179598808
        },
        "probability": 0.527179598808,
        "value": "voice"
    }
},
"lowlevel": {
    "average_loudness": 0.969184577465,
    "barkbands_crest": {
        "dmean": 2.99606609344,
        "dmean2": 4.65436315536,
        "dvar": 9.93353271484,
        "dvar2": 21.5149288177,
        "max": 25.7284698486,
        "mean": 17.4475765228,
        "median": 18.8869152069,
        "min": 3.00416874886,
        "var": 31.0276527405
    },
    "barkbands_flatness_db": {
        "dmean": 0.0418751165271,
        "dmean2": 0.0574874095619,
        "dvar": 0.00178441696335,
        "dvar2": 0.00332330190577,
        "max": 0.490744978189,
        "mean": 0.261873573065,
        "median": 0.256115823984,
        "min": 0.0715492591262,
        "var": 0.00793000310659
    },
    "barkbands_kurtosis": {
        "dmean": 20.41314888,
        "dmean2": 32.1148834229,
        "dvar": 990.280761719,
        "dvar2": 2486.07739258,
        "max": 400.011291504,
        "mean": 31.5199699402,
        "median": 16.5762271881,
        "min": -1.89034163952,
        "var": 2089.8293457
    },
    "barkbands_skewness": {
        "dmean": 1.44808447361,
        "dmean2": 2.18258261681,
        "dvar": 1.93539178371,
        "dvar2": 4.31630659103,
        "max": 18.2766513824,
        "mean": 3.8865673542,
        "median": 3.40884041786,
        "min": -1.55652713776,
        "var": 6.88216543198
    },
    "barkbands_spread": {
        "dmean": 7.21351194382,
        "dmean2": 10.7961683273,
        "dvar": 139.354873657,
        "dvar2": 275.820770264,
        "max": 104.307121277,
        "mean": 12.1101789474,
        "median": 5.75243902206,
        "min": 0.313203901052,
        "var": 263.156005859
    },
    "dissonance": {
        "dmean": 0.0317768231034,
        "dmean2": 0.051764305681,
        "dvar": 0.00090288836509,
        "dvar2": 0.00215947278775,
        "max": 0.498544305563,
        "mean": 0.427290558815,
        "median": 0.438304781914,
        "min": 0.139616310596,
        "var": 0.002681781305
    },
    "dynamic_complexity": 2.76391386986,
    "erbbands_crest": {
        "dmean": 2.90787553787,
        "dmean2": 4.62810516357,
        "dvar": 8.17459106445,
        "dvar2": 17.6266727448,
        "max": 29.846288681,
        "mean": 10.1977548599,
        "median": 8.75074291229,
        "min": 2.29266762733,
        "var": 26.4667987823
    },
    "erbbands_flatness_db": {
        "dmean": 0.031043374911,
        "dmean2": 0.0433833859861,
        "dvar": 0.000865753390826,
        "dvar2": 0.00159735872876,
        "max": 0.383970469236,
        "mean": 0.161722138524,
        "median": 0.157096520066,
        "min": 0.0668696910143,
        "var": 0.00326267094351
    },
    "erbbands_kurtosis": {
        "dmean": 2.41858887672,
        "dmean2": 3.74723982811,
        "dvar": 9.38809680939,
        "dvar2": 20.7641563416,
        "max": 28.2073154449,
        "mean": 2.61478829384,
        "median": 1.12876176834,
        "min": -1.86219930649,
        "var": 19.6465053558
    },
    "erbbands_skewness": {
        "dmean": 0.628077685833,
        "dmean2": 0.917503654957,
        "dvar": 0.339453190565,
        "dvar2": 0.66492754221,
        "max": 4.5439658165,
        "mean": 0.939376473427,
        "median": 0.983901798725,
        "min": -3.36834812164,
        "var": 1.19151043892
    },
    "erbbands_spread": {
        "dmean": 20.1988792419,
        "dmean2": 29.7211894989,
        "dvar": 582.492919922,
        "dvar2": 1070.98681641,
        "max": 192.547683716,
        "mean": 47.1608314514,
        "median": 34.5690765381,
        "min": 2.52844810486,
        "var": 1444.01281738
    },
    "hfc": {
        "dmean": 7.78529691696,
        "dmean2": 10.8432197571,
        "dvar": 210.370407104,
        "dvar2": 358.796569824,
        "max": 150.055755615,
        "mean": 14.9528636932,
        "median": 7.36250495911,
        "min": 0.0527961477637,
        "var": 459.463653564
    },
    "melbands_crest": {
        "dmean": 2.77465772629,
        "dmean2": 4.40110254288,
        "dvar": 8.98883342743,
        "dvar2": 20.5844326019,
        "max": 29.5534591675,
        "mean": 18.6320915222,
        "median": 19.8289070129,
        "min": 5.71300649643,
        "var": 22.4280567169
    },
    "melbands_flatness_db": {
        "dmean": 0.0512832961977,
        "dmean2": 0.0683348998427,
        "dvar": 0.00270185945556,
        "dvar2": 0.00485887937248,
        "max": 0.609262287617,
        "mean": 0.35081037879,
        "median": 0.346635699272,
        "min": 0.0506139919162,
        "var": 0.0126805063337
    },
    "melbands_kurtosis": {
        "dmean": 41.5773544312,
        "dmean2": 63.9386253357,
        "dvar": 4403.55566406,
        "dvar2": 8381.16796875,
        "max": 828.370849609,
        "mean": 65.7069473267,
        "median": 33.121837616,
        "min": -1.27925729752,
        "var": 9019.77148438
    },
    "melbands_skewness": {
        "dmean": 1.82809627056,
        "dmean2": 2.74591898918,
        "dvar": 4.32980966568,
        "dvar2": 7.87896823883,
        "max": 22.4480571747,
        "mean": 5.06252527237,
        "median": 4.21859502792,
        "min": -1.2459332943,
        "var": 12.0478210449
    },
    "melbands_spread": {
        "dmean": 5.28634738922,
        "dmean2": 8.16502189636,
        "dvar": 149.393661499,
        "dvar2": 335.506530762,
        "max": 161.205749512,
        "mean": 8.53278160095,
        "median": 4.34970283508,
        "min": 0.403512954712,
        "var": 197.083389282
    },
    "pitch_salience": {
        "dmean": 0.0864732265472,
        "dmean2": 0.136691972613,
        "dvar": 0.00717548979446,
        "dvar2": 0.0156764276326,
        "max": 0.803821802139,
        "mean": 0.396791547537,
        "median": 0.358602911234,
        "min": 0.0907014012337,
        "var": 0.0234101973474
    },
    "silence_rate_20dB": {
        "dmean": 0,
        "dmean2": 0,
        "dvar": 0,
        "dvar2": 0,
        "max": 1,
        "mean": 1,
        "median": 1,
        "min": 1,
        "var": 0
    },
    "silence_rate_30dB": {
        "dmean": 0.071207433939,
        "dmean2": 0.142525181174,
        "dvar": 0.0661371871829,
        "dvar2": 0.14854760468,
        "max": 1,
        "mean": 0.935808181763,
        "median": 1,
        "min": 0,
        "var": 0.0600707419217
    },
    "silence_rate_60dB": {
        "dmean": 0.0379256978631,
        "dmean2": 0.0759101435542,
        "dvar": 0.0364871583879,
        "dvar2": 0.0809918642044,
        "max": 1,
        "mean": 0.080433100462,
        "median": 0,
        "min": 0,
        "var": 0.0739638805389
    },
    "spectral_centroid": {
        "dmean": 249.450881958,
        "dmean2": 374.508178711,
        "dvar": 152573.375,
        "dvar2": 315974.75,
        "max": 4585.34326172,
        "mean": 669.73840332,
        "median": 474.692962646,
        "min": 118.247650146,
        "var": 344682.15625
    },
    "spectral_complexity": {
        "dmean": 2.96904015541,
        "dmean2": 4.20836544037,
        "dvar": 29.1832466125,
        "dvar2": 41.3375053406,
        "max": 62,
        "mean": 9.1686000824,
        "median": 6,
        "min": 1,
        "var": 76.8128890991
    },
    "spectral_decrease": {
        "dmean": 4.27479163179e-09,
        "dmean2": 6.40890407411e-09,
        "dvar": 4.19890775566e-17,
        "dvar2": 9.52047628834e-17,
        "max": -4.98540167482e-11,
        "mean": -1.27636994307e-08,
        "median": -1.42734881692e-08,
        "min": -5.96606781755e-08,
        "var": 8.43108471556e-17
    },
    "spectral_energy": {
        "dmean": 0.0165783632547,
        "dmean2": 0.0247126929462,
        "dvar": 0.000631453702226,
        "dvar2": 0.00142411713023,
        "max": 0.227852120996,
        "mean": 0.049529440701,
        "median": 0.0545943118632,
        "min": 0.000193329367903,
        "var": 0.00127550156321
    },
    "spectral_energyband_high": {
        "dmean": 0.000480275135487,
        "dmean2": 0.000672337482683,
        "dvar": 9.57129145718e-07,
        "dvar2": 1.6320228724e-06,
        "max": 0.0109152076766,
        "mean": 0.000612449774053,
        "median": 5.52191086172e-05,
        "min": 5.76520903905e-07,
        "var": 2.04416596716e-06
    },
    "spectral_energyband_low": {
        "dmean": 0.0126609699801,
        "dmean2": 0.0188863296062,
        "dvar": 0.000457865709905,
        "dvar2": 0.000975294853561,
        "max": 0.217540353537,
        "mean": 0.0380620844662,
        "median": 0.0461467280984,
        "min": 1.4971692508e-05,
        "var": 0.000898050318938
    },
    "spectral_energyband_middle_high": {
        "dmean": 0.00137402338441,
        "dmean2": 0.00193710427266,
        "dvar": 1.36422813739e-05,
        "dvar2": 2.32616584981e-05,
        "max": 0.065544359386,
        "mean": 0.0021969457157,
        "median": 0.000339021673426,
        "min": 2.71933549811e-06,
        "var": 3.30578222929e-05
    },
    "spectral_energyband_middle_low": {
        "dmean": 0.00615527108312,
        "dmean2": 0.0104935225099,
        "dvar": 0.000241399044171,
        "dvar2": 0.000691681227181,
        "max": 0.142831608653,
        "mean": 0.00992011837661,
        "median": 0.00624130200595,
        "min": 7.01875251252e-05,
        "var": 0.000200018112082
    },
    "spectral_entropy": {
        "dmean": 0.407404571772,
        "dmean2": 0.560939788818,
        "dvar": 0.165686964989,
        "dvar2": 0.302446067333,
        "max": 8.76535606384,
        "mean": 6.99339199066,
        "median": 6.99550151825,
        "min": 5.13430690765,
        "var": 0.592758595943
    },
    "spectral_flux": {
        "dmean": 0.0367348454893,
        "dmean2": 0.0584076531231,
        "dvar": 0.00206133513711,
        "dvar2": 0.00453727506101,
        "max": 0.397549808025,
        "mean": 0.0854484885931,
        "median": 0.0645323172212,
        "min": 0.00743112992495,
        "var": 0.00418386003003
    },
    "spectral_kurtosis": {
        "dmean": 4.86474275589,
        "dmean2": 6.90237092972,
        "dvar": 39.4100837708,
        "dvar2": 82.9053726196,
        "max": 100.328033447,
        "mean": 9.52787971497,
        "median": 6.40239143372,
        "min": -1.08695840836,
        "var": 100.657310486
    },
    "spectral_rms": {
        "dmean": 0.00113902147859,
        "dmean2": 0.00159259932116,
        "dvar": 2.05802712117e-06,
        "dvar2": 3.95694996769e-06,
        "max": 0.0149095524102,
        "mean": 0.00636209500954,
        "median": 0.00729813287035,
        "min": 0.000434297166066,
        "var": 7.84511303209e-06
    },
    "spectral_rolloff": {
        "dmean": 476.963897705,
        "dmean2": 828.204284668,
        "dvar": 1961595.875,
        "dvar2": 4450202,
        "max": 11154.1992188,
        "mean": 648.858764648,
        "median": 236.865234375,
        "min": 86.1328125,
        "var": 2148205.5
    },
    "spectral_skewness": {
        "dmean": 0.580000638962,
        "dmean2": 0.791696250439,
        "dvar": 0.364157915115,
        "dvar2": 0.721330761909,
        "max": 8.24933433533,
        "mean": 2.36200737953,
        "median": 2.20984101295,
        "min": -0.000734594592359,
        "var": 1.30841624737
    },
    "spectral_spread": {
        "dmean": 1602913,
        "dmean2": 2157708.75,
        "dvar": 3.1317777449e+12,
        "dvar2": 5.75475233587e+12,
        "max": 15134715,
        "mean": 5539743,
        "median": 4622311,
        "min": 1243378.5,
        "var": 9.263382528e+12
    },
    "spectral_strongpeak": {
        "dmean": 0.227043226361,
        "dmean2": 0.366254448891,
        "dvar": 0.216319158673,
        "dvar2": 0.43026599288,
        "max": 10.9302558899,
        "mean": 0.680103719234,
        "median": 0.685410857201,
        "min": 0.0120694106445,
        "var": 0.420727044344
    },
    "zerocrossingrate": {
        "dmean": 0.0145218316466,
        "dmean2": 0.0163734965026,
        "dvar": 0.000441579497419,
        "dvar2": 0.000550188240595,
        "max": 0.3134765625,
        "mean": 0.0330377221107,
        "median": 0.02197265625,
        "min": 0.00244140625,
        "var": 0.00146022241097
    },
    "barkbands": {
        "dmean": [0.000116922674351, 0.0107202725485, 0.00302596390247, 0.00206633494236, 0.00274450355209, 0.000988901010714, 0.000838024134282, 0.000896009500138, 0.000404681864893, 0.000162853102665, 0.000116358234663, 0.00021425964951, 0.000168048252817, 0.000277356797596, 0.000196676686755, 0.000172355343238, 0.000158512732014, 0.0002081887651, 7.06576538505e-05, 5.20623907505e-05, 7.29659150238e-05, 6.06605754001e-05, 7.09016603651e-05, 0.000110052038508, 0.000135297901579, 4.97606706631e-05, 4.32074021006e-09],
        "dmean2": [0.00018969962548, 0.0161719527096, 0.00523202540353, 0.00375044019893, 0.00479035405442, 0.00171033164952, 0.00125488697086, 0.00136214564554, 0.000597216945607, 0.000262738118181, 0.000180762202945, 0.000294942175969, 0.000258034706349, 0.000406775187002, 0.000276694539934, 0.000258029234828, 0.000244748545811, 0.000291253003525, 0.000100544180896, 7.63385251048e-05, 0.00011510270997, 8.94442127901e-05, 0.000101444020402, 0.00015480494767, 0.000195377404452, 7.23835255485e-05, 8.04265454235e-09],
        "dvar": [7.22042159396e-08, 0.000273865531199, 8.44162495923e-05, 4.93771658512e-05, 6.80976518197e-05, 2.88899059342e-06, 6.53062943456e-06, 9.22409890336e-06, 2.67379846264e-06, 2.79404730463e-07, 9.30087793449e-08, 4.88322598358e-07, 2.35032402429e-07, 1.62005926541e-06, 7.91334400674e-07, 4.15290173805e-07, 2.5117600444e-07, 5.34551361397e-07, 5.39991908965e-08, 3.74208539711e-08, 9.93218876033e-08, 1.81813870626e-08, 2.02968930552e-08, 4.11020195656e-08, 7.4955231355e-08, 1.23972494492e-08, 8.46260082629e-16],
        "dvar2": [1.30079513383e-07, 0.000565093068872, 0.000227144235396, 0.000143401673995, 0.000195846048882, 7.40094355933e-06, 1.53254241013e-05, 2.23244715016e-05, 6.0124157244e-06, 6.63585751681e-07, 2.0633670772e-07, 8.45781187309e-07, 5.34955120202e-07, 2.266623369e-06, 1.1629393839e-06, 7.14837653959e-07, 5.8959466287e-07, 1.05594779143e-06, 1.05061964462e-07, 5.88747219865e-08, 2.41266974399e-07, 3.61800083226e-08, 3.74440034534e-08, 7.09299001755e-08, 1.32367063088e-07, 2.28694148063e-08, 2.49703047037e-15],
        "max": [0.00659492379054, 0.169030338526, 0.103935755789, 0.0636269897223, 0.0842010304332, 0.0319493152201, 0.0537834875286, 0.0517353639007, 0.0345348566771, 0.0108734006062, 0.00415889173746, 0.0135614033788, 0.00534877832979, 0.0476251356304, 0.0279318913817, 0.0182204823941, 0.00811605341733, 0.00927427876741, 0.00328060798347, 0.00575414672494, 0.00697741191834, 0.00230288272724, 0.00168672576547, 0.00273805204779, 0.00450456375256, 0.00164550787304, 5.51227515189e-07],
        "mean": [0.000174453671207, 0.0328208953142, 0.00385312782601, 0.00219022482634, 0.00326000945643, 0.00125210231636, 0.00135648145806, 0.00129966379609, 0.000472686224384, 0.000229970581131, 0.000146878111991, 0.000312157673761, 0.000198940833798, 0.000367459753761, 0.000221477195737, 0.000225735115237, 0.000190490478417, 0.000217985274503, 8.74046672834e-05, 7.12191758794e-05, 7.88417819422e-05, 7.02084435034e-05, 8.51966251503e-05, 0.000132404849865, 0.000159681614605, 5.37291562068e-05, 2.95742630385e-09],
        "median": [2.41506422753e-05, 0.0410667732358, 0.00252949027345, 0.00114791549277, 0.00154536450282, 0.000599083665293, 0.000415437156335, 9.23581537791e-05, 4.5023200073e-05, 3.57901117241e-05, 2.41404213739e-05, 2.83902700176e-05, 1.61954703799e-05, 2.10940106626e-05, 1.69771210494e-05, 1.60258732649e-05, 1.73904536496e-05, 1.63864624483e-05, 7.95928463049e-06, 3.88562330045e-06, 5.17087528351e-06, 7.79779111326e-06, 6.42702389086e-06, 9.78869502433e-06, 1.17608215078e-05, 4.25647567681e-06, 6.56363685625e-10],
        "min": [5.11163156247e-09, 3.31461546921e-06, 3.5288660456e-06, 7.33654860596e-06, 7.18111823517e-06, 1.44105001709e-06, 1.87329226264e-06, 6.28727832463e-07, 2.0174765325e-07, 2.44180654363e-07, 2.17501124666e-07, 2.16122330698e-07, 2.61330853846e-07, 2.28186877393e-07, 1.45915208805e-07, 9.53522771852e-08, 1.01079486114e-07, 1.16798076988e-07, 9.1502194266e-08, 3.26812639173e-08, 3.69925992061e-08, 4.43231371605e-08, 2.93100743676e-08, 1.17765512897e-08, 1.38265736638e-08, 8.78933800741e-11, 1.29540900576e-11],
        "var": [1.92343890149e-07, 0.000627062283456, 6.37290941086e-05, 3.06542351609e-05, 4.67430327262e-05, 4.03878175348e-06, 9.91637534753e-06, 1.81121122296e-05, 3.03417505165e-06, 5.29031865426e-07, 1.54915582584e-07, 1.28879548811e-06, 3.28513266368e-07, 4.93145944347e-06, 1.5208337345e-06, 1.07238474811e-06, 3.29979769731e-07, 6.79452909935e-07, 9.1378261402e-08, 9.94800899434e-08, 1.1303480818e-07, 3.10193897235e-08, 3.59013263562e-08, 9.55867918151e-08, 1.72041580981e-07, 2.11802024808e-08, 4.52641436821e-16]
    },
    "erbbands": {
        "dmean": [0.233285486698, 2.68958616257, 3.79121851921, 4.9298620224, 11.1927127838, 7.003490448, 7.89606809616, 6.27607917786, 6.31770038605, 21.482667923, 15.7265701294, 7.54331970215, 7.61563968658, 3.43806123734, 5.80933332443, 8.46865749359, 7.53432321548, 11.2529020309, 12.4301137924, 9.52608585358, 7.85420322418, 9.18719577789, 13.3594884872, 4.06284618378, 3.31022381783, 2.40722155571, 2.30006837845, 3.11650800705, 2.02946639061, 2.19727158546, 2.04109239578, 2.00938153267, 1.96407878399, 1.67097854614, 0.928236544132, 0.329331189394, 0.0719382017851, 0.00444652931765, 0.000101360499684, 2.38301399804e-05],
        "dmean2": [0.345796734095, 4.09494400024, 6.21292114258, 8.73974132538, 20.6813640594, 11.3428564072, 13.0060348511, 10.8087730408, 9.96876430511, 33.0692977905, 22.4714012146, 10.9980306625, 12.3402376175, 5.2606754303, 8.46638393402, 11.944070816, 11.7016563416, 16.6492156982, 18.4084358215, 13.4675521851, 11.283162117, 13.887254715, 18.6947154999, 5.82772636414, 4.55799818039, 3.45061540604, 3.550147295, 5.06266736984, 3.0763194561, 3.09114956856, 2.90330910683, 2.82366704941, 2.79514813423, 2.39051508904, 1.36470210552, 0.476651370525, 0.106940545142, 0.00674562295899, 0.00014874554472, 3.36727716785e-05],
        "dvar": [0.149331063032, 17.7900905609, 96.7669525146, 157.789611816, 2060.69506836, 172.473724365, 135.385559082, 206.990493774, 300.336181641, 5206.078125, 3206.59545898, 645.136779785, 949.542663574, 72.4453201294, 243.748352051, 841.694091797, 477.257019043, 1861.56054688, 2283.47509766, 1195.70617676, 524.188354492, 740.153503418, 2079.66601562, 170.166854858, 156.422866821, 70.5736465454, 80.0015945435, 175.383529663, 22.8665409088, 22.5332431793, 16.3653583527, 14.1830615997, 14.6837568283, 13.2280788422, 3.13400912285, 0.423887789249, 0.0359798073769, 0.000196784938453, 7.27894686747e-08, 1.37269462464e-09],
        "dvar2": [0.295482128859, 37.8238182068, 253.334716797, 451.365112305, 5960.01611328, 458.253234863, 323.32434082, 472.956970215, 765.138061523, 12802.8378906, 6238.36083984, 1374.60144043, 2367.54516602, 169.617950439, 516.021484375, 1702.77148438, 1051.5904541, 3374.8659668, 3981.27001953, 2153.95874023, 964.154541016, 1662.43103027, 4143.30957031, 286.356811523, 281.104095459, 113.349365234, 178.355072021, 435.441802979, 45.2521133423, 44.9290466309, 29.7910289764, 26.2821788788, 25.4680023193, 24.8809871674, 5.94720506668, 0.79728525877, 0.0666078403592, 0.000385521387216, 1.37151303647e-07, 2.88406032389e-09],
        "max": [3.12433862686, 44.8181800842, 109.667976379, 114.819137573, 427.442016602, 127.752456665, 150.586334229, 333.833709717, 284.349304199, 1211.72558594, 1194.83898926, 443.926055908, 706.624023438, 93.1924819946, 267.302734375, 561.427734375, 273.430603027, 1416.83325195, 1364.01184082, 884.473327637, 328.329956055, 374.780639648, 574.449768066, 129.803726196, 330.385070801, 198.83102417, 139.376464844, 288.5105896, 64.2129135132, 98.9494934082, 41.3432121277, 51.8598480225, 56.7809715271, 66.8749160767, 22.3830394745, 9.76221466064, 2.68045926094, 0.165357142687, 0.00294541381299, 0.000357818295015],
        "mean": [0.72250777483, 7.99854230881, 7.0635061264, 6.60374546051, 9.79754829407, 10.4763202667, 12.0322122574, 8.06793689728, 12.1374044418, 30.1224479675, 25.7001552582, 9.6564245224, 10.1843252182, 5.17988729477, 7.79368638992, 11.6259670258, 9.62580394745, 14.8234138489, 15.2478561401, 13.404501915, 9.88108730316, 11.5430297852, 14.0944747925, 5.24608564377, 4.29317998886, 3.3670873642, 2.75785207748, 3.28251361847, 2.37149953842, 2.57427144051, 2.46273398399, 2.35655903816, 2.3573281765, 2.00250411034, 1.01218247414, 0.356334656477, 0.0785125568509, 0.00439157197252, 0.000125361868413, 6.30522845313e-05],
        "median": [0.61243969202, 10.2515249252, 6.12101078033, 4.27040624619, 3.0308110714, 5.77684402466, 6.75255441666, 3.7499370575, 6.68004989624, 2.71706366539, 2.4225051403, 1.23777318001, 1.40587687492, 1.24985766411, 0.946301281452, 1.20812380314, 0.952460110188, 0.978316783905, 1.16712450981, 0.983887970448, 0.924677550793, 1.07050156593, 1.03229832649, 0.5112388134, 0.34223780036, 0.214451804757, 0.183395057917, 0.222637265921, 0.236675873399, 0.280173629522, 0.171261847019, 0.180218353868, 0.165217578411, 0.124478496611, 0.0856407061219, 0.0314893238246, 0.0049502318725, 0.000210407510167, 3.19324790325e-05, 6.09485177847e-05],
        "min": [7.79470356065e-05, 0.000873403041624, 0.00451096799225, 0.0214690491557, 0.0356589891016, 0.0167786329985, 0.0331624001265, 0.00818079337478, 0.0109260100871, 0.0348335243762, 0.0140266353264, 0.00672274501994, 0.0110984230414, 0.00993998162448, 0.0122159011662, 0.0108978394419, 0.0160671342164, 0.0121575873345, 0.0103990556672, 0.0102649061009, 0.00744185596704, 0.00728596653789, 0.0086473133415, 0.00619045086205, 0.00449589639902, 0.00231619598344, 0.000904473068658, 0.000894287484698, 0.00140598311555, 0.00123860046733, 0.000774895597715, 0.000327103683958, 0.000492226157803, 0.000377818738343, 4.82608447783e-05, 4.02103833039e-05, 2.57083570432e-06, 2.44722514253e-07, 1.28502477992e-07, 2.21402970624e-07],
        "var": [0.390387028456, 39.6735954285, 92.1245498657, 112.511421204, 1237.97058105, 201.699325562, 233.618179321, 283.880981445, 401.731201172, 6586.60644531, 8195.28710938, 871.278320312, 1478.60290527, 124.237701416, 501.17489624, 1555.18591309, 713.168151855, 4958.79296875, 4684.24902344, 3808.00805664, 980.706176758, 1092.63427734, 2695.37915039, 285.361053467, 328.530487061, 194.955230713, 115.731163025, 193.486160278, 40.1368141174, 35.8059501648, 29.0070724487, 27.0817146301, 36.9824676514, 32.425113678, 5.42377996445, 0.762014567852, 0.0573492012918, 0.000242211317527, 1.03089412562e-07, 2.73764610981e-09]
    },
    "gfcc": {
        "mean": [-54.5656051636, 115.874610901, -59.9873466492, 39.9154930115, -46.0283508301, 25.4457988739, -45.5727081299, 15.7646541595, -17.1355686188, 4.71145772934, -9.58568000793, 3.53079843521, -7.87300777435],
        "cov": [[6319.09423828, -2017.95727539, -815.86541748, 348.040649414, -64.7939910889, 513.386108398, -153.124069214, 415.477600098, -191.155807495, 253.818878174, -316.342590332, 138.50428772, -190.221923828], [-2017.95727539, 2169.29614258, -31.2030067444, -587.703063965, 493.172607422, -387.016723633, 354.261138916, -114.724945068, 315.130889893, -147.250961304, 296.418212891, -150.093017578, 161.368606567], [-815.86541748, -31.2030067444, 1102.10864258, 340.503082275, 23.7822360992, 110.204978943, 44.9177589417, -30.397151947, 74.7716445923, 66.9083786011, 103.877670288, 94.7154464722, 62.3244590759], [348.040649414, -587.703063965, 340.503082275, 597.555419922, 28.9237709045, 99.3466644287, -109.628700256, 8.86092662811, 4.5834941864, 43.2707252502, 23.3144359589, 54.3927726746, 52.955581665], [-64.7939910889, 493.172607422, 23.7822360992, 28.9237709045, 474.568450928, -1.36546599865, 78.1838684082, -11.0973529816, 137.987487793, -27.3456707001, 86.3797531128, -2.29240942001, 85.7222900391], [513.386108398, -387.016723633, 110.204978943, 99.3466644287, -1.36546599865, 266.683135986, -23.0734634399, 12.1770038605, -25.8201522827, 45.6582450867, -54.8346977234, 40.8080787659, -24.5132961273], [-153.124069214, 354.261138916, 44.9177589417, -109.628700256, 78.1838684082, -23.0734634399, 250.053787231, 32.7712287903, 36.0696792603, 3.36894059181, 67.9125823975, -23.0959186554, 16.692861557], [415.477600098, -114.724945068, -30.397151947, 8.86092662811, -11.0973529816, 12.1770038605, 32.7712287903, 129.131622314, 16.7893772125, 20.0203437805, -15.5918645859, 4.66051435471, -15.6230802536], [-191.155807495, 315.130889893, 74.7716445923, 4.5834941864, 137.987487793, -25.8201522827, 36.0696792603, 16.7893772125, 167.121368408, 5.73709774017, 56.6622657776, -15.5516748428, 50.3743858337], [253.818878174, -147.250961304, 66.9083786011, 43.2707252502, -27.3456707001, 45.6582450867, 3.36894059181, 20.0203437805, 5.73709774017, 98.8181686401, -0.833210468292, 7.2923951149, -14.4372339249], [-316.342590332, 296.418212891, 103.877670288, 23.3144359589, 86.3797531128, -54.8346977234, 67.9125823975, -15.5918645859, 56.6622657776, -0.833210468292, 134.104446411, -13.1117677689, 45.9690475464], [138.50428772, -150.093017578, 94.7154464722, 54.3927726746, -2.29240942001, 40.8080787659, -23.0959186554, 4.66051435471, -15.5516748428, 7.2923951149, -13.1117677689, 89.8515853882, 14.2164764404], [-190.221923828, 161.368606567, 62.3244590759, 52.955581665, 85.7222900391, -24.5132961273, 16.692861557, -15.6230802536, 50.3743858337, -14.4372339249, 45.9690475464, 14.2164764404, 97.3403549194]],
        "icov": [[0.000426935701398, 0.00026342383353, 0.000441801792476, -0.000102496378531, -0.000319148181006, -0.000362964201486, -9.93134672171e-05, -0.000867332448252, 4.61877025373e-05, -0.000643980747554, -2.26806205319e-05, -0.000418759736931, 0.000190433798707], [0.00026342383353, 0.00594063661993, -0.000930413196329, 0.00511682126671, -0.00302709662355, 0.00353591796011, -0.00266494206153, 0.00314189237542, -0.00489656627178, 0.00317064719275, -0.00427814153954, 0.00353535194881, -0.00249560503289], [0.000441801792476, -0.000930413196329, 0.00220767757855, -0.00195470685139, 0.000717322633136, -0.00155932153575, -0.000219746259972, -0.00086920132162, 0.000149201005115, -0.0017232846003, -3.9245125663e-05, -0.00266292993911, 0.00100410892628], [-0.000102496378531, 0.00511682126671, -0.00195470685139, 0.00743380375206, -0.00278758374043, 0.00278923287988, -0.00055228167912, 0.00238643307239, -0.003442754969, 0.0027217939496, -0.0046095685102, 0.00381109397858, -0.00403485074639], [-0.000319148181006, -0.00302709662355, 0.000717322633136, -0.00278758374043, 0.00501486286521, -0.00234610703774, 0.00052691536257, -0.000523418770172, -5.37820669706e-05, -0.000224322619033, 0.001156688435, -0.00210365140811, 2.58532109001e-05], [-0.000362964201486, 0.00353591796011, -0.00155932153575, 0.00278923287988, -0.00234610703774, 0.00808253418654, -0.00208623870276, 0.00338440993801, -0.00282865180634, 0.000997202703729, -0.0001165716385, 0.00149233802222, -0.000638756027911], [-9.93134672171e-05, -0.00266494206153, -0.000219746259972, -0.00055228167912, 0.00052691536257, -0.00208623870276, 0.00746905663982, -0.00396630493924, 0.00339014525525, -0.0018291992601, -0.001050986466, -0.000102730373328, 0.000243699643761], [-0.000867332448252, 0.00314189237542, -0.00086920132162, 0.00238643307239, -0.000523418770172, 0.00338440993801, -0.00396630493924, 0.0138769103214, -0.00589642580599, 0.00231912196614, -0.000791457656305, 0.00142123992555, 0.000137023729621], [4.61877025373e-05, -0.00489656627178, 0.000149201005115, -0.003442754969, -5.37820669706e-05, -0.00282865180634, 0.00339014525525, -0.00589642580599, 0.0145776923746, -0.00463607441634, 0.00213453406468, -0.000433396169683, -0.00138405198231], [-0.000643980747554, 0.00317064719275, -0.0017232846003, 0.0027217939496, -0.000224322619033, 0.000997202703729, -0.0018291992601, 0.00231912196614, -0.00463607441634, 0.0156221566722, -0.00369624537416, 0.00275133550167, 0.000302502594423], [-2.26806205319e-05, -0.00427814153954, -3.9245125663e-05, -0.0046095685102, 0.001156688435, -0.0001165716385, -0.001050986466, -0.000791457656305, 0.00213453406468, -0.00369624537416, 0.016530925408, -0.00123485631775, -0.000693297362886], [-0.000418759736931, 0.00353535194881, -0.00266292993911, 0.00381109397858, -0.00210365140811, 0.00149233802222, -0.000102730373328, 0.00142123992555, -0.000433396169683, 0.00275133550167, -0.00123485631775, 0.0178134441376, -0.00595949823037], [0.000190433798707, -0.00249560503289, 0.00100410892628, -0.00403485074639, 2.58532109001e-05, -0.000638756027911, 0.000243699643761, 0.000137023729621, -0.00138405198231, 0.000302502594423, -0.000693297362886, -0.00595949823037, 0.0180901754647]]
    },
    "melbands": {
        "dmean": [0.00263689993881, 0.00254501821473, 0.00106192636304, 0.000671671994496, 0.000263898808043, 0.000155631380039, 0.000112476009235, 0.000234833438299, 0.000115014845505, 4.80934286315e-05, 3.86945139326e-05, 1.40619440572e-05, 1.80707411346e-05, 2.44453985943e-05, 1.70003077073e-05, 1.81872619578e-05, 2.27330529015e-05, 2.29518773267e-05, 1.64648754435e-05, 1.36182079586e-05, 9.01824114408e-06, 9.33322644414e-06, 1.31818533191e-05, 8.85319968802e-06, 3.09731717607e-06, 2.39012865677e-06, 2.2905521746e-06, 1.51681274474e-06, 1.27635905756e-06, 2.12834106605e-06, 1.64532855251e-06, 1.17862884963e-06, 1.1721122064e-06, 1.26624013319e-06, 1.24671248614e-06, 1.31078070353e-06, 1.21432640299e-06, 1.30689511479e-06, 1.53216205945e-06, 1.45928493112e-06],
        "dmean2": [0.00393964862451, 0.00387938902713, 0.00190306617878, 0.0011895095231, 0.000425878795795, 0.000269465701422, 0.000173357097083, 0.000360029633157, 0.000166741127032, 7.09470623406e-05, 6.21909348411e-05, 2.11176720768e-05, 2.72867182503e-05, 3.29439317284e-05, 2.53964262811e-05, 2.85233018076e-05, 3.39691141562e-05, 3.40399419656e-05, 2.20046731556e-05, 1.96692781174e-05, 1.306179729e-05, 1.45437870742e-05, 1.96332002815e-05, 1.21050152302e-05, 4.53188476968e-06, 3.41493409906e-06, 3.16324985761e-06, 2.20405604523e-06, 1.90436821867e-06, 3.5516754906e-06, 2.68096755462e-06, 1.8412844156e-06, 1.71746091837e-06, 1.80625761459e-06, 1.86405236491e-06, 1.84419150173e-06, 1.75590605522e-06, 1.91854155673e-06, 2.24422183237e-06, 2.15230534195e-06],
        "dvar": [1.73065418494e-05, 2.417628275e-05, 1.08358372017e-05, 5.12252336193e-06, 1.3801408727e-07, 1.08471787996e-07, 9.19076583727e-08, 5.74770069761e-07, 2.02836886842e-07, 3.26496696346e-08, 2.38923494322e-08, 1.21240095741e-09, 2.21870632977e-09, 6.54559029201e-09, 3.61840180041e-09, 3.10591730113e-09, 9.76985514711e-09, 9.90979120985e-09, 6.66358124235e-09, 3.31177951729e-09, 7.10987990704e-10, 6.94944490842e-10, 1.88999660367e-09, 9.56788093198e-10, 9.56854664946e-11, 7.2029743281e-11, 9.74753402994e-11, 3.26855417732e-11, 2.28686253961e-11, 1.20870341513e-10, 3.67658681277e-11, 8.2864349063e-12, 7.91706630809e-12, 7.01867253552e-12, 6.53434771569e-12, 6.47297363279e-12, 5.27099804776e-12, 6.43879871295e-12, 1.2683218191e-11, 9.97426967408e-12],
        "dvar2": [3.46848864865e-05, 5.82714055781e-05, 3.11142284772e-05, 1.48136414282e-05, 3.25597056872e-07, 2.60941618535e-07, 2.2553457768e-07, 1.43600345837e-06, 3.63867002307e-07, 7.30353519884e-08, 5.9628014526e-08, 2.76903344698e-09, 5.08646325059e-09, 9.85190062863e-09, 6.68136346249e-09, 7.0527876872e-09, 1.62558890793e-08, 1.61575073321e-08, 1.0224617597e-08, 5.90053872429e-09, 1.45185541367e-09, 1.64942082215e-09, 3.7124949781e-09, 1.98632155168e-09, 1.8550744274e-10, 1.46194598094e-10, 1.51146858918e-10, 5.85060125347e-11, 4.66800868792e-11, 3.27497029495e-10, 8.52154041775e-11, 1.77951819946e-11, 1.68410112245e-11, 1.40125012288e-11, 1.31162450692e-11, 1.2068357598e-11, 1.04173770304e-11, 1.15310590937e-11, 2.31512222587e-11, 2.03216731637e-11],
        "max": [0.0372596979141, 0.049866925925, 0.0274576060474, 0.0225754864514, 0.00504094688222, 0.00744871376082, 0.0052414429374, 0.0109561635181, 0.00927646271884, 0.00416520889848, 0.00360705144703, 0.000449792685686, 0.000509953359142, 0.00200065085664, 0.00107331271283, 0.000718188646715, 0.00342770991847, 0.00347044528462, 0.00272490503266, 0.00188506848644, 0.000326662586303, 0.000287102127913, 0.000490341102704, 0.000392521382309, 0.000105480154161, 0.000161281510373, 0.000299973151414, 0.000172776562977, 6.7663131631e-05, 0.000256509694736, 0.000111086395918, 3.01843356283e-05, 6.12229123362e-05, 4.85500240757e-05, 2.55098293565e-05, 2.65907565336e-05, 3.62400642189e-05, 3.29452777805e-05, 7.49636237742e-05, 5.36290099262e-05],
        "mean": [0.00833811517805, 0.00650461064652, 0.00123336084653, 0.000738313770853, 0.000430529238656, 0.000204409720027, 0.000199675720069, 0.000329774455167, 0.000186264267541, 5.66533926758e-05, 5.10932477482e-05, 2.09991048905e-05, 2.28432709264e-05, 3.52096249117e-05, 2.34544950217e-05, 2.14937917917e-05, 3.00926785712e-05, 2.75226357189e-05, 1.89488928299e-05, 1.80799252121e-05, 9.90848002402e-06, 1.11513745651e-05, 1.46886295624e-05, 9.2319532996e-06, 3.70861403098e-06, 2.96438656733e-06, 3.01124032376e-06, 2.0517215944e-06, 1.52356255967e-06, 2.00601743927e-06, 1.83315398772e-06, 1.33304638439e-06, 1.29885847855e-06, 1.45914941641e-06, 1.41759721828e-06, 1.50897380991e-06, 1.3809911934e-06, 1.52623317717e-06, 1.88282979252e-06, 1.64468917774e-06],
        "median": [0.00961865670979, 0.00733908312395, 0.000706446066033, 0.000324711116264, 0.000260207831161, 9.70006221905e-05, 8.898487431e-05, 2.16210955841e-05, 1.18936332001e-05, 5.85803081776e-06, 6.50207175568e-06, 4.78734409626e-06, 3.3866888316e-06, 2.64270806838e-06, 2.98545592159e-06, 1.59623391482e-06, 1.73346745669e-06, 1.90509842923e-06, 1.18976583963e-06, 1.20043944207e-06, 9.18546334105e-07, 1.01101511518e-06, 1.12349482606e-06, 6.59043280393e-07, 3.33222089921e-07, 2.43654625365e-07, 1.67783426264e-07, 1.14342824986e-07, 9.00472016951e-08, 1.00995777075e-07, 1.21192357483e-07, 1.21417116361e-07, 1.53449079221e-07, 1.50038118818e-07, 9.03525219087e-08, 9.99222748987e-08, 1.07208094846e-07, 1.14167264087e-07, 1.03315386468e-07, 1.03310973998e-07],
        "min": [1.07092398594e-06, 2.73458022093e-06, 4.34549383499e-06, 1.43460329127e-06, 1.22217875287e-06, 1.57300050319e-07, 2.46788658842e-07, 2.03686113309e-07, 6.60157013499e-08, 3.16708366199e-08, 5.30919059827e-08, 2.88537371773e-08, 3.90722370014e-08, 2.76045533099e-08, 3.90538872352e-08, 2.57091929967e-08, 1.9934471851e-08, 1.34125004436e-08, 1.24088161968e-08, 1.02783515032e-08, 7.40591854509e-09, 6.65366117758e-09, 4.62653382272e-09, 4.4962193968e-09, 4.42561010061e-09, 2.37567920891e-09, 7.5776307451e-10, 4.31192886952e-10, 2.8343841163e-10, 4.81188311419e-10, 5.26041543658e-10, 6.96717350479e-10, 7.85029374839e-10, 5.88849746741e-10, 3.70463271171e-10, 9.37865271555e-11, 9.19192083559e-11, 2.54027042457e-11, 3.36849437232e-10, 3.04814767177e-13],
        "var": [4.17728515458e-05, 3.5825989471e-05, 6.99285828887e-06, 3.31738533532e-06, 2.49561423971e-07, 1.46848165627e-07, 1.34416907827e-07, 7.5022751389e-07, 4.9295209692e-07, 3.94048242924e-08, 3.75952566856e-08, 2.15176609863e-09, 3.58473006834e-09, 2.01684517975e-08, 6.06173378159e-09, 4.29684154923e-09, 2.80380003659e-08, 2.20759837077e-08, 1.31529267478e-08, 9.90942616852e-09, 9.4751229085e-10, 1.01257990881e-09, 2.62964072739e-09, 1.18958132234e-09, 1.45162368237e-10, 1.239269104e-10, 2.41590553118e-10, 8.75940639466e-11, 3.83100669243e-11, 1.03459685263e-10, 4.86194001725e-11, 1.34823176928e-11, 1.12887815415e-11, 1.12444064476e-11, 1.00617509116e-11, 1.12744839506e-11, 9.66632763416e-12, 1.46648092975e-11, 3.43708533856e-11, 2.02301387447e-11]
    },
    "mfcc": {
        "mean": [-717.008666992, 147.579956055, 46.2357902527, 26.4455986023, 30.3088436127, 11.0342264175, 0.826201319695, 9.14967060089, 1.02823138237, -0.784906327724, 5.36791658401, 3.19827389717, 1.44326364994],
        "cov": [[7036.078125, -2278.25756836, -810.904724121, -254.112762451, 63.2727165222, 45.1262664795, 80.904335022, 68.5974807739, 157.650802612, 128.624267578, 39.1796302795, 46.0092658997, -119.664520264], [-2278.25756836, 2509.00732422, -429.137329102, -54.9447135925, -29.6666965485, -101.627296448, 50.9375, 61.6033172607, 30.5521469116, 74.5210800171, 39.9376564026, 57.811794281, 112.964927673], [-810.904724121, -429.137329102, 1027.24768066, 201.585021973, 54.067150116, 127.554351807, 17.7725658417, 4.70118618011, -11.035449028, -33.6971626282, 26.1801586151, 22.2245559692, 76.2779769897], [-254.112762451, -54.9447135925, 201.585021973, 381.168212891, 157.290023804, 22.7958755493, 27.6216869354, 8.03822994232, 6.03334522247, 20.4462051392, -18.1792812347, 17.3511734009, 62.398311615], [63.2727165222, -29.6666965485, 54.067150116, 157.290023804, 376.542022705, 115.495658875, -26.9127349854, 29.6207847595, 24.9769763947, 37.9236412048, -4.30032300949, -8.81256198883, -5.90181875229], [45.1262664795, -101.627296448, 127.554351807, 22.7958755493, 115.495658875, 212.679763794, 40.2358436584, 14.1235151291, 23.6380405426, 6.09937381744, 24.1433124542, -7.25278139114, -21.1065692902], [80.904335022, 50.9375, 17.7725658417, 27.6216869354, -26.9127349854, 40.2358436584, 163.040359497, 34.6408081055, 13.1855783463, 10.0647935867, 22.8131408691, 18.1862373352, 16.8068695068], [68.5974807739, 61.6033172607, 4.70118618011, 8.03822994232, 29.6207847595, 14.1235151291, 34.6408081055, 113.608795166, 38.324092865, 1.53706085682, 5.97371292114, 9.55702972412, 8.77083301544], [157.650802612, 30.5521469116, -11.035449028, 6.03334522247, 24.9769763947, 23.6380405426, 13.1855783463, 38.324092865, 98.4077529907, 29.6792488098, 10.0072069168, 13.4297800064, 14.2039070129], [128.624267578, 74.5210800171, -33.6971626282, 20.4462051392, 37.9236412048, 6.09937381744, 10.0647935867, 1.53706085682, 29.6792488098, 101.69355011, 24.7023239136, 23.8391551971, 11.2344884872], [39.1796302795, 39.9376564026, 26.1801586151, -18.1792812347, -4.30032300949, 24.1433124542, 22.8131408691, 5.97371292114, 10.0072069168, 24.7023239136, 82.3467178345, 21.1519317627, 6.91357660294], [46.0092658997, 57.811794281, 22.2245559692, 17.3511734009, -8.81256198883, -7.25278139114, 18.1862373352, 9.55702972412, 13.4297800064, 23.8391551971, 21.1519317627, 77.3143768311, 32.9457626343], [-119.664520264, 112.964927673, 76.2779769897, 62.398311615, -5.90181875229, -21.1065692902, 16.8068695068, 8.77083301544, 14.2039070129, 11.2344884872, 6.91357660294, 32.9457626343, 102.318473816]],
        "icov": [[0.000386617699405, 0.000492770981509, 0.000498151523061, 0.000243753122049, -0.000154668698087, 1.74965393285e-08, -0.000268176023383, -0.000233628845308, -0.000333672767738, -0.000387533073081, -0.000168203681824, -0.000352472998202, -0.000343014864484], [0.000492770981509, 0.00111746892799, 0.00087037216872, 0.00039597786963, -0.000240911511355, 7.49134487705e-05, -0.000409853382735, -0.000536904728506, -0.000280220381683, -0.000685860344674, -0.000390845205402, -0.000472654093755, -0.0011400654912], [0.000498151523061, 0.00087037216872, 0.00208482285962, -0.000391869223677, 0.000174204207724, -0.00106155569665, 6.93709225743e-05, -0.000548865413293, -4.18715944761e-06, 9.52661048359e-06, -0.000783995899837, -0.000581132364459, -0.00162722938694], [0.000243753122049, 0.00039597786963, -0.000391869223677, 0.0044912439771, -0.00224386085756, 0.00101983302739, -0.00153948296793, 0.000414113805164, -1.90580285562e-05, -0.000681724748574, 0.00127906363923, -0.0003915981506, -0.00218343618326], [-0.000154668698087, -0.000240911511355, 0.000174204207724, -0.00224386085756, 0.00487016467378, -0.0028726044111, 0.00219497457147, -0.00144795631059, 0.000403283163905, -0.00139268720523, 0.000379354984034, 0.000659164623357, 0.000634597730823], [1.74965393285e-08, 7.49134487705e-05, -0.00106155569665, 0.00101983302739, -0.0028726044111, 0.00783817190677, -0.00264953146689, 0.00100540334824, -0.00184095383156, 0.000804191222414, -0.00159677956253, 0.000596194237005, 0.00197016075253], [-0.000268176023383, -0.000409853382735, 6.93709225743e-05, -0.00153948296793, 0.00219497457147, -0.00264953146689, 0.00839265715331, -0.00248603289947, 0.000917300523724, -0.000317708094371, -0.00115724094212, -0.00043336948147, -0.000434153422248], [-0.000233628845308, -0.000536904728506, -0.000548865413293, 0.000414113805164, -0.00144795631059, 0.00100540334824, -0.00248603289947, 0.0116691933945, -0.00433131027967, 0.00229032943025, 3.54504445568e-05, -0.00050777127035, 0.000519009423442], [-0.000333672767738, -0.000280220381683, -4.18715944761e-06, -1.90580285562e-05, 0.000403283163905, -0.00184095383156, 0.000917300523724, -0.00433131027967, 0.0139357391745, -0.00337719265372, 0.000415356218582, -0.000141533790156, -0.00174825300928], [-0.000387533073081, -0.000685860344674, 9.52661048359e-06, -0.000681724748574, -0.00139268720523, 0.000804191222414, -0.000317708094371, 0.00229032943025, -0.00337719265372, 0.013686391525, -0.00314501300454, -0.00243355915882, 0.00061621714849], [-0.000168203681824, -0.000390845205402, -0.000783995899837, 0.00127906363923, 0.000379354984034, -0.00159677956253, -0.00115724094212, 3.54504445568e-05, 0.000415356218582, -0.00314501300454, 0.015369287692, -0.00285201705992, 8.62705492182e-05], [-0.000352472998202, -0.000472654093755, -0.000581132364459, -0.0003915981506, 0.000659164623357, 0.000596194237005, -0.00043336948147, -0.00050777127035, -0.000141533790156, -0.00243355915882, -0.00285201705992, 0.0173256192356, -0.00404178630561], [-0.000343014864484, -0.0011400654912, -0.00162722938694, -0.00218343618326, 0.000634597730823, 0.00197016075253, -0.000434153422248, 0.000519009423442, -0.00174825300928, 0.00061621714849, 8.62705492182e-05, -0.00404178630561, 0.0151160471141]]
    },
    "spectral_contrast_coeffs": {
        "dmean": [0.0511617325246, 0.0586253590882, 0.0382462628186, 0.034040465951, 0.0299202613533, 0.0291930660605],
        "dmean2": [0.0839227810502, 0.0939496904612, 0.0590522289276, 0.0525831244886, 0.0468278452754, 0.0454824864864],
        "dvar": [0.00215123267844, 0.00212329579517, 0.00113172782585, 0.00109891488682, 0.00073648430407, 0.000661410624161],
        "dvar2": [0.00568793294951, 0.00499373255298, 0.00212385039777, 0.00218481384218, 0.00151540304068, 0.00155159377027],
        "max": [-0.375109165907, -0.407212495804, -0.402055650949, -0.474364906549, -0.572604238987, -0.524860143661],
        "mean": [-0.681317448616, -0.670879721642, -0.803341805935, -0.81604218483, -0.794773459435, -0.80069899559],
        "median": [-0.692725896835, -0.673600792885, -0.819352686405, -0.836819291115, -0.805685818195, -0.809685349464],
        "min": [-0.830954372883, -0.880175292492, -0.922230482101, -0.934898614883, -0.898040056229, -0.886277198792],
        "var": [0.00407446827739, 0.00730543164536, 0.00559450499713, 0.00447010714561, 0.00267499033362, 0.00209116982296]
    },
    "spectral_contrast_valleys": {
        "dmean": [0.400318920612, 0.438379913568, 0.413136392832, 0.472767591476, 0.494904130697, 0.791007757187],
        "dmean2": [0.626629114151, 0.691668510437, 0.639851927757, 0.693309545517, 0.671063899994, 0.982602655888],
        "dvar": [0.121478453279, 0.143662437797, 0.187049493194, 0.249846965075, 0.249128848314, 0.527068138123],
        "dvar2": [0.242967814207, 0.326383620501, 0.402669072151, 0.471602916718, 0.415217161179, 0.955368995667],
        "max": [-5.16728258133, -5.27043247223, -5.5045208931, -5.56041908264, -5.44206047058, -7.89523744583],
        "mean": [-6.57240390778, -7.38827848434, -8.19528770447, -8.47716903687, -8.85643672943, -10.8136453629],
        "median": [-6.3458647728, -7.39409446716, -8.23912620544, -8.53800678253, -8.91470623016, -10.8595552444],
        "min": [-9.70885276794, -9.85199260712, -10.2622041702, -10.515039444, -11.4098892212, -14.8481369019],
        "var": [0.650936603546, 0.427636623383, 0.667952060699, 0.867857515812, 1.0782905817, 2.06819105148]
    }
},
"metadata": {
    "audio_properties": {
        "analysis_sample_rate": 44100,
        "bit_rate": 96000,
        "equal_loudness": 0,
        "length": 30.0000228882,
        "lossless": 0,
        "replay_gain": -11.985666275,
        "sample_rate": 44100,
        "codec": "mp3",
        "downmix": "mix",
        "md5_encoded": "3c94c46dcca436b1752faa0ba19acade"
    },
    "tags": {
        "file_name": "4EmrbKpQotKGCH0IWCnAOP.mp3"
    },
    "version": {
        "essentia": "2.1-beta3",
        "essentia_git_sha": "Undefined",
        "extractor": "music 1.0"
    }
},
"rhythm": {
    "beats_count": 44,
    "beats_loudness": {
        "dmean": 0.0407834388316,
        "dmean2": 0.0728799328208,
        "dvar": 0.00128526298795,
        "dvar2": 0.00345528684556,
        "max": 0.209642440081,
        "mean": 0.0861299932003,
        "median": 0.0783116593957,
        "min": 0.00285905459896,
        "var": 0.00127481273375
    },
    "bpm": 89.8079223633,
    "bpm_histogram_first_peak_bpm": {
        "dmean": 0,
        "dmean2": 0,
        "dvar": 0,
        "dvar2": 0,
        "max": 91,
        "mean": 91,
        "median": 91,
        "min": 91,
        "var": 0
    },
    "bpm_histogram_first_peak_spread": {
        "dmean": 0,
        "dmean2": 0,
        "dvar": 0,
        "dvar2": 0,
        "max": 0.441176474094,
        "mean": 0.441176474094,
        "median": 0.441176474094,
        "min": 0.441176474094,
        "var": 0
    },
    "bpm_histogram_first_peak_weight": {
        "dmean": 0,
        "dmean2": 0,
        "dvar": 0,
        "dvar2": 0,
        "max": 0.441860467196,
        "mean": 0.441860467196,
        "median": 0.441860467196,
        "min": 0.441860467196,
        "var": 0
    },
    "bpm_histogram_second_peak_bpm": {
        "dmean": 0,
        "dmean2": 0,
        "dvar": 0,
        "dvar2": 0,
        "max": 85,
        "mean": 85,
        "median": 85,
        "min": 85,
        "var": 0
    },
    "bpm_histogram_second_peak_spread": {
        "dmean": 0,
        "dmean2": 0,
        "dvar": 0,
        "dvar2": 0,
        "max": 0.111111164093,
        "mean": 0.111111164093,
        "median": 0.111111164093,
        "min": 0.111111164093,
        "var": 0
    },
    "bpm_histogram_second_peak_weight": {
        "dmean": 0,
        "dmean2": 0,
        "dvar": 0,
        "dvar2": 0,
        "max": 0.186046510935,
        "mean": 0.186046510935,
        "median": 0.186046510935,
        "min": 0.186046510935,
        "var": 0
    },
    "danceability": 1.39365756512,
    "onset_rate": 5.43119859695,
    "beats_loudness_band_ratio": {
        "dmean": [0.284021019936, 0.0637793466449, 0.103273957968, 0.0699733421206, 0.112551487982, 0.0400012545288],
        "dmean2": [0.549462378025, 0.118508689106, 0.19875214994, 0.135377302766, 0.225921973586, 0.0771305933595],
        "dvar": [0.0267008952796, 0.00215448462404, 0.0205053333193, 0.00451165996492, 0.0185582116246, 0.00113142246846],
        "dvar2": [0.0499733388424, 0.0065322718583, 0.0616788752377, 0.00951303075999, 0.050375290215, 0.00324653368443],
        "max": [0.992283701897, 0.274411469698, 0.596300303936, 0.35635086894, 0.668604791164, 0.131363168359],
        "mean": [0.75636100769, 0.0620468631387, 0.0730367600918, 0.0413482934237, 0.0576664432883, 0.0287557523698],
        "median": [0.829688191414, 0.0515684895217, 0.0208076499403, 0.0166045501828, 0.00618684478104, 0.0149259567261],
        "min": [0.0188718494028, 0.00395759660751, 0.000991139444523, 7.14256530046e-05, 0.00013578866492, 3.67174034182e-05],
        "var": [0.0564034469426, 0.00250288122334, 0.0161440130323, 0.00484714098275, 0.0122628575191, 0.00116470071953]
    },
    "beats_position": [0.696598649025, 1.39319729805, 2.08979582787, 2.79800438881, 3.50621318817, 4.22603178024, 4.93424034119, 5.64244890213, 6.35065746307, 7.05886602402, 7.72063493729, 8.38240337372, 9.05578231812, 9.72916126251, 10.3909292221, 11.0526981354, 11.7260770798, 12.3994560242, 13.0612239838, 13.722992897, 14.3847618103, 15.0465307236, 15.7199087143, 16.3932876587, 17.0666656494, 17.7400455475, 18.390203476, 19.0519733429, 19.7253513336, 20.3871192932, 21.0488891602, 21.7106571198, 22.3840351105, 23.0574150085, 23.7191829681, 24.3809528351, 25.0543308258, 25.7277088165, 26.3894786835, 27.0512466431, 27.7246246338, 28.3980045319, 29.0597724915, 29.7215423584]
},
"tonal": {
    "chords_changes_rate": 0.0664605870843,
    "chords_number_rate": 0.00927357003093,
    "chords_strength": {
        "dmean": 0.0122558232397,
        "dmean2": 0.012283667922,
        "dvar": 0.000109884342237,
        "dvar2": 0.000145352692925,
        "max": 0.69977003336,
        "mean": 0.423060566187,
        "median": 0.424867480993,
        "min": 0.22990141809,
        "var": 0.00718056643382
    },
    "hpcp_entropy": {
        "dmean": 0.771101295948,
        "dmean2": 1.29528224468,
        "dvar": 0.443606883287,
        "dvar2": 1.18877804279,
        "max": 4.40486717224,
        "mean": 1.97800922394,
        "median": 1.87397825718,
        "min": 0.0433629080653,
        "var": 0.791818022728
    },
    "key_strength": 0.503368675709,
    "tuning_diatonic_strength": 0.451880902052,
    "tuning_equal_tempered_deviation": 0.113432571292,
    "tuning_frequency": 437.465789795,
    "tuning_nontempered_energy_ratio": 0.731953561306,
    "hpcp": {
        "dmean": [0.0461201258004, 0.0475620515645, 0.0526168569922, 0.0624757371843, 0.0838396400213, 0.126815602183, 0.175013691187, 0.165501251817, 0.123652219772, 0.0986263602972, 0.104248940945, 0.167745605111, 0.157486557961, 0.185602262616, 0.0977874845266, 0.0672100186348, 0.0559946261346, 0.0929678305984, 0.122328981757, 0.111188836396, 0.0907058343291, 0.0850437134504, 0.0808495357633, 0.0631064400077, 0.0405327863991, 0.0376303046942, 0.0698405876756, 0.0910492092371, 0.0670590549707, 0.035446152091, 0.02787906304, 0.0356618985534, 0.0647298768163, 0.093345798552, 0.079677850008, 0.0618053525686],
        "dmean2": [0.087755933404, 0.091124728322, 0.101222924888, 0.118261657655, 0.160981461406, 0.228073492646, 0.308706402779, 0.296132922173, 0.226071119308, 0.191641807556, 0.198325395584, 0.302856147289, 0.27664488554, 0.324048101902, 0.182821780443, 0.129390507936, 0.106016479433, 0.155890524387, 0.214415952563, 0.194695234299, 0.168202608824, 0.15379345417, 0.136999487877, 0.115553215146, 0.0760850086808, 0.0711047276855, 0.12571464479, 0.158651411533, 0.117879040539, 0.0649147480726, 0.0501092262566, 0.0645247101784, 0.110569961369, 0.156942918897, 0.140833005309, 0.114708311856],
        "dvar": [0.0186881776899, 0.0225037168711, 0.0276069138199, 0.0317825116217, 0.0432820022106, 0.0544500611722, 0.0738790631294, 0.0753493160009, 0.0441617146134, 0.0502254851162, 0.0471457839012, 0.0570588484406, 0.0750071778893, 0.0601417422295, 0.0430460236967, 0.0362057425082, 0.0235467273742, 0.0322814546525, 0.067045673728, 0.0401195064187, 0.038751360029, 0.0436197072268, 0.0376288630068, 0.0237151812762, 0.0159795060754, 0.0096830483526, 0.0270591601729, 0.0390221960843, 0.0223922543228, 0.0102111203596, 0.00975048914552, 0.0106614017859, 0.0199151281267, 0.0385440886021, 0.0305176787078, 0.0233902968466],
        "dvar2": [0.0534438379109, 0.0652746036649, 0.0801011994481, 0.0916891470551, 0.123913750052, 0.156473264098, 0.197914034128, 0.192654579878, 0.128245458007, 0.14998985827, 0.133803263307, 0.160625010729, 0.172617256641, 0.155471816659, 0.121430672705, 0.103991642594, 0.0686402395368, 0.0808212310076, 0.126524522901, 0.102500878274, 0.1164656654, 0.0950828492641, 0.086219869554, 0.0674859806895, 0.0456538535655, 0.0296106413007, 0.0751115754247, 0.10362137109, 0.0607361607254, 0.0286658145487, 0.0271698087454, 0.0294694621116, 0.0484105683863, 0.0885146558285, 0.0665539428592, 0.0634074285626],
        "max": [1, 1, 1, 1, 1, 1, 1, 1, 1, 1, 1, 1, 1, 1, 1, 1, 1, 1, 1, 1, 1, 1, 1, 1, 1, 0.800512909889, 1, 1, 1, 1, 1, 1, 1, 1, 1, 1],
        "mean": [0.0270254407078, 0.0269374959171, 0.0304347574711, 0.0359667390585, 0.0502516925335, 0.0988058745861, 0.196087628603, 0.195337116718, 0.100921049714, 0.0600590519607, 0.0618007034063, 0.211008965969, 0.402782738209, 0.267423272133, 0.064723521471, 0.0399055220187, 0.0366976968944, 0.105768382549, 0.186223879457, 0.126198977232, 0.062535263598, 0.0929748266935, 0.0836047828197, 0.0432628467679, 0.0258627962321, 0.0253740251064, 0.0536176115274, 0.0760253742337, 0.0523345097899, 0.024565467611, 0.0192886907607, 0.0243834126741, 0.0573476590216, 0.106820128858, 0.0964239090681, 0.047147333622],
        "median": [0.000898780825082, 0.000688685977366, 0.000816601968836, 0.00106245849747, 0.00161153171211, 0.00774871371686, 0.0217308551073, 0.0234530400485, 0.00595337245613, 0.00159604800865, 0.00211273971945, 0.0512398630381, 0.110624879599, 0.0889820978045, 0.012100645341, 0.00171032606158, 0.00210351753049, 0.00781183224171, 0.0203135944903, 0.0223922915757, 0.00875430461019, 0.00454448815435, 0.00500396592543, 0.00284719234332, 0.0015481824521, 0.00141472846735, 0.00194372690748, 0.00198524584994, 0.00136967259459, 0.00105755298864, 0.000797104090452, 0.00158176163677, 0.00983371213078, 0.0220751892775, 0.0151628851891, 0.00270545645617],
        "min": [2.58038426182e-06, 2.27135774367e-06, 1.22403953355e-05, 2.04906646104e-05, 2.85416922452e-06, 1.916362271e-05, 7.93819563114e-05, 3.95814204239e-05, 7.61662886362e-06, 1.96997939383e-06, 1.41251803143e-06, 7.18240607966e-06, 7.65950608184e-06, 5.35797607881e-06, 6.31347165836e-06, 4.78105766888e-06, 8.72097461979e-06, 4.6657063649e-05, 9.6261537692e-06, 4.40777839685e-05, 1.55126763275e-05, 1.22136689242e-05, 1.31551023514e-05, 1.12743364298e-05, 6.50400124869e-06, 6.3079114625e-06, 6.19575848759e-06, 9.01676230569e-06, 1.27922658066e-05, 4.88342175231e-06, 3.44939530805e-06, 3.04486366076e-06, 1.22260216813e-05, 9.80200911727e-06, 7.81108519732e-06, 2.01346338145e-05],
        "var": [0.0107853999361, 0.0125728677958, 0.0159390680492, 0.017955807969, 0.0262863300741, 0.0469657704234, 0.101137556136, 0.104282125831, 0.0404943041503, 0.0300032328814, 0.0299372076988, 0.0712946727872, 0.197294980288, 0.0949124544859, 0.027262320742, 0.0210862010717, 0.0149381849915, 0.0445833541453, 0.118734121323, 0.0494254045188, 0.0259930118918, 0.0602457597852, 0.0510252714157, 0.0175604894757, 0.00977667141706, 0.00612168759108, 0.022075638175, 0.0374187491834, 0.0189833790064, 0.00682409480214, 0.00661221705377, 0.00732247997075, 0.0192875750363, 0.0509947128594, 0.0494817607105, 0.0189284682274]
    },
    "chords_histogram": [0.618238031864, 0, 9.58268928528, 0, 2.78207111359, 0, 0, 0, 0, 0, 0, 0, 0, 0, 0, 0, 0, 1.08191657066, 0, 38.0216369629, 0, 24.5749607086, 23.3384857178, 0],
    "thpcp": [1, 0.663939237595, 0.160690903664, 0.0990745574236, 0.0911104008555, 0.262594133615, 0.462343245745, 0.313317745924, 0.155258059502, 0.230831205845, 0.207567945123, 0.107409879565, 0.0642102882266, 0.0629968047142, 0.133117944002, 0.188750326633, 0.129932358861, 0.0609893761575, 0.0478885732591, 0.0605373829603, 0.142378643155, 0.265205323696, 0.239394336939, 0.117054007947, 0.0670968219638, 0.0668784752488, 0.0755612254143, 0.0892956331372, 0.124761283398, 0.245308116078, 0.486832261086, 0.484968930483, 0.250559508801, 0.149110287428, 0.153434336185, 0.523877859116],
    "chords_key": "C#",
    "chords_scale": "minor",
    "key_key": "F#",
    "key_scale": "major"
}
}